README.md
setup.py
tlist/__init__.py
tlist/tlist.py
tlist.egg-info/PKG-INFO
tlist.egg-info/SOURCES.txt
tlist.egg-info/dependency_links.txt
tlist.egg-info/top_level.txt